losantmqtt/RootCA.crt
losantmqtt/__init__.py
losantmqtt/device.py
losant_mqtt-1.2.1.dist-info/LICENSE
losant_mqtt-1.2.1.dist-info/METADATA
losant_mqtt-1.2.1.dist-info/WHEEL
losant_mqtt-1.2.1.dist-info/top_level.txt
losant_mqtt-1.2.1.dist-info/RECORD
