Metadata-Version: 2.1
Name: losant-mqtt
Version: 1.2.1
Summary: An MQTT client for Losant
Home-page: https://github.com/Losant/losant-mqtt-python
Author: Losant
Author-email: hello@losant.com
License: MIT
Keywords: MQTT,Losant,IoT
Classifier: Development Status :: 4 - Beta
Classifier: Intended Audience :: Developers
Classifier: Operating System :: MacOS :: MacOS X
Classifier: Operating System :: Microsoft :: Windows
Classifier: Operating System :: POSIX
Classifier: Topic :: Communications
Classifier: Topic :: Internet
Classifier: Topic :: Software Development :: Libraries
Classifier: License :: OSI Approved :: MIT License
Classifier: Programming Language :: Python
Classifier: Programming Language :: Python :: 2.7
Classifier: Programming Language :: Python :: 3
License-File: LICENSE
Requires-Dist: paho-mqtt <2,>=1.6.1
